[
    {
        "messegeid": 0,
        "username": "192.168.1.24",
        "message": "test ",
        "router": "2",
        "Students_name": "mohammed",
        "path": "notactive"
    },
    {
        "messegeid": 1,
        "username": "192.168.1.24",
        "message": "what do you think?",
        "router": "2",
        "Students_name": "mohammed",
        "path": "notactive"
    },
    {
        "messegeid": 2,
        "username": "192.168.1.90",
        "message": "testing chat",
        "router": "1",
        "Students_name": "sam",
        "path": "notactive"
    }
]